pyramid_soy/__init__.py
pyramid_soy-0.0.1.data/scripts/setup.py
pyramid_soy-0.0.1.dist-info/top_level.txt
pyramid_soy-0.0.1.dist-info/METADATA
pyramid_soy-0.0.1.dist-info/WHEEL
pyramid_soy-0.0.1.dist-info/metadata.json
pyramid_soy-0.0.1.dist-info/DESCRIPTION.rst
pyramid_soy-0.0.1.dist-info/RECORD
