Metadata-Version: 2.0
Name: pyramid-soy
Version: 0.0.1
Summary: Simple soy wrapper with simple cache.
Home-page: http://github.com/winkidney
Author: winkidney
Author-email: winkidney@gmail.com
License: UNKNOWN
Keywords: web pyramid pylons
Platform: UNKNOWN
Classifier: Programming Language :: Python
Classifier: Framework :: Pyramid
Classifier: Topic :: Internet :: WWW/HTTP
Classifier: Topic :: Internet :: WWW/HTTP :: WSGI :: Application
Requires-Dist: soy
